rstdeprecated
