Metadata-Version: 1.0
Name: rstdeprecated
Version: 0.16.4
Summary: Robotics Systems Types - Deprecated
Home-page: https://code.cor-lab.org/projects/rst
Author: Johannes Wienke
Author-email: jwienke@techfak.uni-bielefeld.de
License: GPLv3
Platform: UNKNOWN
